[
  {
    "id":1,
    "name":"CALL教室A",
    "building":"1号館",
    "floor":"B1",
    "capacity":"",
    "feature":""
  },
  {
    "id":2,
    "name":"CALL教室B",
    "building":"1号館",
    "floor":"B1",
    "capacity":"",
    "feature":""
  },
  {
    "id":3,
    "name":"CALL教室C",
    "building":"1号館",
    "floor":"B1",
    "capacity":"",
    "feature":""
  },
  {
    "id":4,
    "name":"CALL教室D",
    "building":"1号館",
    "floor":"B1",
    "capacity":"",
    "feature":""
  },
  {
    "id":5,
    "name":"ラボ1",
    "building":"1号館",
    "floor":"1",
    "capacity":"",
    "feature":""
  },
  {
    "id":6,
    "name":"ラボ2",
    "building":"1号館",
    "floor":"1",
    "capacity":"",
    "feature":""
  },
  {
    "id":7,
    "name":"114教室",
    "building":"1号館",
    "floor":"1",
    "capacity":"510",
    "feature":""
  },
  {
    "id":8,
    "name":"117教室",
    "building":"1号館",
    "floor":"1",
    "capacity":"117",
    "feature":""
  },
  {
    "id":9,
    "name":"118教室",
    "building":"1号館",
    "floor":"1",
    "capacity":"100",
    "feature":""
  },
  {
    "id":10,
    "name":"121教室",
    "building":"1号館",
    "floor":"2",
    "capacity":"100",
    "feature":""
  },
  {
    "id":11,
    "name":"122教室",
    "building":"1号館",
    "floor":"2",
    "capacity":"100",
    "feature":""
  },
  {
    "id":12,
    "name":"123教室",
    "building":"1号館",
    "floor":"2",
    "capacity":"78",
    "feature":""
  },
  {
    "id":13,
    "name":"124教室",
    "building":"1号館",
    "floor":"2",
    "capacity":"167",
    "feature":""
  },
  {
    "id":14,
    "name":"125教室",
    "building":"1号館",
    "floor":"2",
    "capacity":"100",
    "feature":""
  },
  {
    "id":15,
    "name":"131教室",
    "building":"1号館",
    "floor":"3",
    "capacity":"510",
    "feature":""
  },
  {
    "id":16,
    "name":"132教室",
    "building":"1号館",
    "floor":"3",
    "capacity":"305",
    "feature":""
  },
  {
    "id":17,
    "name":"133教室",
    "building":"1号館",
    "floor":"3",
    "capacity":"302",
    "feature":""
  },
  {
    "id":18,
    "name":"シアター201",
    "building":"2号館",
    "floor":"B1",
    "capacity":"200",
    "feature":""
  },
  {
    "id":19,
    "name":"スタジオ202",
    "building":"2号館",
    "floor":"B1",
    "capacity":"168",
    "feature":""
  },
  {
    "id":20,
    "name":"スタジオ211",
    "building":"2号館",
    "floor":"1",
    "capacity":"208",
    "feature":""
  },
  {
    "id":21,
    "name":"221教室",
    "building":"2号館",
    "floor":"2",
    "capacity":"30",
    "feature":""
  },
  {
    "id":22,
    "name":"222教室",
    "building":"2号館",
    "floor":"2",
    "capacity":"30",
    "feature":""
  },
  {
    "id":23,
    "name":"223教室",
    "building":"2号館",
    "floor":"2",
    "capacity":"30",
    "feature":""
  },
  {
    "id":24,
    "name":"224教室",
    "building":"2号館",
    "floor":"2",
    "capacity":"30",
    "feature":""
  },
  {
    "id":25,
    "name":"225教室",
    "building":"2号館",
    "floor":"2",
    "capacity":"30",
    "feature":""
  },
  {
    "id":26,
    "name":"226教室",
    "building":"2号館",
    "floor":"2",
    "capacity":"30",
    "feature":""
  },
  {
    "id":27,
    "name":"227教室",
    "building":"2号館",
    "floor":"2",
    "capacity":"30",
    "feature":""
  },
  {
    "id":28,
    "name":"331教室",
    "building":"3号館",
    "floor":"3",
    "capacity":"",
    "feature":""
  },
  {
    "id":29,
    "name":"332教室",
    "building":"3号館",
    "floor":"3",
    "capacity":"",
    "feature":""
  },
  {
    "id":30,
    "name":"333教室",
    "building":"3号館",
    "floor":"3",
    "capacity":"",
    "feature":""
  },
  {
    "id":31,
    "name":"334教室",
    "building":"3号館",
    "floor":"3",
    "capacity":"",
    "feature":""
  },
  {
    "id":32,
    "name":"335教室",
    "building":"3号館",
    "floor":"3",
    "capacity":"",
    "feature":""
  },
  {
    "id":33,
    "name":"336教室",
    "building":"3号館",
    "floor":"3",
    "capacity":"",
    "feature":""
  },
  {
    "id":34,
    "name":"337教室",
    "building":"3号館",
    "floor":"3",
    "capacity":"",
    "feature":""
  },
  {
    "id":35,
    "name":"338教室",
    "building":"3号館",
    "floor":"3",
    "capacity":"",
    "feature":""
  },
  {
    "id":36,
    "name":"339教室",
    "building":"3号館",
    "floor":"3",
    "capacity":"",
    "feature":""
  },
  {
    "id":37,
    "name":"410教室",
    "building":"4号館",
    "floor":"1",
    "capacity":"240",
    "feature":""
  },
  {
    "id":38,
    "name":"420教室",
    "building":"4号館",
    "floor":"2",
    "capacity":"244",
    "feature":""
  },
  {
    "id":39,
    "name":"421教室",
    "building":"4号館",
    "floor":"2",
    "capacity":"36",
    "feature":""
  },
  {
    "id":40,
    "name":"422教室",
    "building":"4号館",
    "floor":"2",
    "capacity":"42",
    "feature":""
  },
  {
    "id":41,
    "name":"423教室",
    "building":"4号館",
    "floor":"2",
    "capacity":"80",
    "feature":""
  },
  {
    "id":42,
    "name":"424教室",
    "building":"4号館",
    "floor":"2",
    "capacity":"80",
    "feature":""
  },
  {
    "id":43,
    "name":"425教室",
    "building":"4号館",
    "floor":"2",
    "capacity":"64",
    "feature":""
  },
  {
    "id":44,
    "name":"426教室",
    "building":"4号館",
    "floor":"2",
    "capacity":"120",
    "feature":""
  },
  {
    "id":45,
    "name":"427教室",
    "building":"4号館",
    "floor":"2",
    "capacity":"90",
    "feature":""
  },
  {
    "id":46,
    "name":"428教室",
    "building":"4号館",
    "floor":"2",
    "capacity":"120",
    "feature":""
  },
  {
    "id":47,
    "name":"429教室",
    "building":"4号館",
    "floor":"2",
    "capacity":"120",
    "feature":""
  },
  {
    "id":48,
    "name":"ゼミ44A",
    "building":"4号館",
    "floor":"4",
    "capacity":"",
    "feature":""
  },
  {
    "id":49,
    "name":"ゼミ44B",
    "building":"4号館",
    "floor":"4",
    "capacity":"",
    "feature":""
  },
  {
    "id":50,
    "name":"511教室",
    "building":"5号館",
    "floor":"1",
    "capacity":"187",
    "feature":""
  },
  {
    "id":51,
    "name":"521教室",
    "building":"5号館",
    "floor":"2",
    "capacity":"80",
    "feature":""
  },
  {
    "id":52,
    "name":"522教室",
    "building":"5号館",
    "floor":"2",
    "capacity":"80",
    "feature":""
  },
  {
    "id":53,
    "name":"523教室",
    "building":"5号館",
    "floor":"2",
    "capacity":"80",
    "feature":""
  },
  {
    "id":54,
    "name":"524教室",
    "building":"5号館",
    "floor":"2",
    "capacity":"80",
    "feature":""
  },
  {
    "id":55,
    "name":"525教室",
    "building":"5号館",
    "floor":"2",
    "capacity":"374",
    "feature":""
  },
  {
    "id":56,
    "name":"526教室",
    "building":"5号館",
    "floor":"2",
    "capacity":"88",
    "feature":""
  },
  {
    "id":57,
    "name":"527教室",
    "building":"5号館",
    "floor":"2",
    "capacity":"88",
    "feature":""
  },
  {
    "id":58,
    "name":"528教室",
    "building":"5号館",
    "floor":"2",
    "capacity":"374",
    "feature":""
  },
  {
    "id":59,
    "name":"ゼミ51",
    "building":"5号館",
    "floor":"3",
    "capacity":"",
    "feature":""
  },
  {
    "id":60,
    "name":"ゼミ52",
    "building":"5号館",
    "floor":"3",
    "capacity":"",
    "feature":""
  },
  {
    "id":61,
    "name":"ゼミ53",
    "building":"5号館",
    "floor":"3",
    "capacity":"",
    "feature":""
  },
  {
    "id":62,
    "name":"ゼミ54",
    "building":"5号館",
    "floor":"3",
    "capacity":"",
    "feature":""
  },
  {
    "id":63,
    "name":"ゼミ55",
    "building":"5号館",
    "floor":"3",
    "capacity":"",
    "feature":""
  },
  {
    "id":64,
    "name":"ゼミ56",
    "building":"5号館",
    "floor":"3",
    "capacity":"",
    "feature":""
  },
  {
    "id":65,
    "name":"701教室",
    "building":"7号館",
    "floor":"B1",
    "capacity":"204",
    "feature":""
  },
  {
    "id":66,
    "name":"702教室",
    "building":"7号館",
    "floor":"B1",
    "capacity":"204",
    "feature":""
  },
  {
    "id":67,
    "name":"711教室",
    "building":"7号館",
    "floor":"1",
    "capacity":"90",
    "feature":""
  },
  {
    "id":68,
    "name":"712教室",
    "building":"7号館",
    "floor":"1",
    "capacity":"90",
    "feature":""
  },
  {
    "id":69,
    "name":"713教室",
    "building":"7号館",
    "floor":"1",
    "capacity":"100",
    "feature":""
  },
  {
    "id":70,
    "name":"714教室",
    "building":"7号館",
    "floor":"1",
    "capacity":"90",
    "feature":""
  },
  {
    "id":71,
    "name":"721教室",
    "building":"7号館",
    "floor":"2",
    "capacity":"90",
    "feature":""
  },
  {
    "id":72,
    "name":"722教室",
    "building":"7号館",
    "floor":"2",
    "capacity":"90",
    "feature":""
  },
  {
    "id":73,
    "name":"723教室",
    "building":"7号館",
    "floor":"2",
    "capacity":"90",
    "feature":""
  },
  {
    "id":74,
    "name":"724教室",
    "building":"7号館",
    "floor":"2",
    "capacity":"90",
    "feature":""
  },
  {
    "id":75,
    "name":"725教室",
    "building":"7号館",
    "floor":"2",
    "capacity":"90",
    "feature":""
  },
  {
    "id":76,
    "name":"ゼミ70",
    "building":"7号館",
    "floor":"3",
    "capacity":"",
    "feature":""
  },
  {
    "id":77,
    "name":"ゼミ71",
    "building":"7号館",
    "floor":"3",
    "capacity":"",
    "feature":""
  },
  {
    "id":78,
    "name":"ゼミ72",
    "building":"7号館",
    "floor":"3",
    "capacity":"",
    "feature":""
  },
  {
    "id":79,
    "name":"ゼミ73",
    "building":"7号館",
    "floor":"3",
    "capacity":"",
    "feature":""
  },
  {
    "id":80,
    "name":"ゼミ74",
    "building":"7号館",
    "floor":"3",
    "capacity":"",
    "feature":""
  },
  {
    "id":81,
    "name":"ゼミ75",
    "building":"7号館",
    "floor":"3",
    "capacity":"",
    "feature":""
  },
  {
    "id":82,
    "name":"ゼミ76",
    "building":"7号館",
    "floor":"3",
    "capacity":"",
    "feature":""
  },
  {
    "id":83,
    "name":"ゼミ77",
    "building":"7号館",
    "floor":"3",
    "capacity":"",
    "feature":""
  },
  {
    "id":84,
    "name":"ゼミ78",
    "building":"7号館",
    "floor":"3",
    "capacity":"",
    "feature":""
  },
  {
    "id":85,
    "name":"ゼミ79",
    "building":"7号館",
    "floor":"3",
    "capacity":"",
    "feature":""
  },
  {
    "id":86,
    "name":"811教室",
    "building":"8号館",
    "floor":"1",
    "capacity":"144",
    "feature":""
  },
  {
    "id":87,
    "name":"812教室",
    "building":"8号館",
    "floor":"1",
    "capacity":"144",
    "feature":""
  },
  {
    "id":88,
    "name":"813教室",
    "building":"8号館",
    "floor":"1",
    "capacity":"144",
    "feature":""
  },
  {
    "id":89,
    "name":"814教室",
    "building":"8号館",
    "floor":"1",
    "capacity":"144",
    "feature":""
  },
  {
    "id":90,
    "name":"821教室",
    "building":"8号館",
    "floor":"2",
    "capacity":"132",
    "feature":""
  },
  {
    "id":91,
    "name":"822教室",
    "building":"8号館",
    "floor":"2",
    "capacity":"132",
    "feature":""
  },
  {
    "id":92,
    "name":"823教室",
    "building":"8号館",
    "floor":"2",
    "capacity":"132",
    "feature":""
  },
  {
    "id":93,
    "name":"824教室",
    "building":"8号館",
    "floor":"2",
    "capacity":"132",
    "feature":""
  },
  {
    "id":94,
    "name":"端末室A",
    "building":"9号館",
    "floor":"4",
    "capacity":"",
    "feature":""
  },
  {
    "id":95,
    "name":"端末室B",
    "building":"9号館",
    "floor":"4",
    "capacity":"",
    "feature":""
  },
  {
    "id":96,
    "name":"端末室C",
    "building":"9号館",
    "floor":"4",
    "capacity":"",
    "feature":""
  },
  {
    "id":97,
    "name":"端末室D",
    "building":"9号館",
    "floor":"4",
    "capacity":"",
    "feature":""
  },
  {
    "id":98,
    "name":"端末室E",
    "building":"9号館",
    "floor":"4",
    "capacity":"",
    "feature":""
  },
  {
    "id":99,
    "name":"端末室F",
    "building":"9号館",
    "floor":"4",
    "capacity":"",
    "feature":""
  },
  {
    "id":100,
    "name":"ゼミ95A",
    "building":"9号館",
    "floor":"5",
    "capacity":"",
    "feature":""
  },
  {
    "id":101,
    "name":"ゼミ95B",
    "building":"9号館",
    "floor":"5",
    "capacity":"",
    "feature":""
  },
  {
    "id":102,
    "name":"ゼミ95C",
    "building":"9号館",
    "floor":"5",
    "capacity":"",
    "feature":""
  },
  {
    "id":103,
    "name":"ゼミ95D",
    "building":"9号館",
    "floor":"5",
    "capacity":"",
    "feature":""
  },
  {
    "id":104,
    "name":"ゼミ95E",
    "building":"9号館",
    "floor":"5",
    "capacity":"",
    "feature":""
  },
  {
    "id":105,
    "name":"ゼミ95F",
    "building":"9号館",
    "floor":"5",
    "capacity":"",
    "feature":""
  },
  {
    "id":106,
    "name":"ゼミ95G",
    "building":"9号館",
    "floor":"5",
    "capacity":"",
    "feature":""
  },
  {
    "id":107,
    "name":"ゼミ95H",
    "building":"9号館",
    "floor":"5",
    "capacity":"",
    "feature":""
  },
  {
    "id":108,
    "name":"ゼミ95I",
    "building":"9号館",
    "floor":"5",
    "capacity":"",
    "feature":""
  },
  {
    "id":109,
    "name":"ゼミ95J",
    "building":"9号館",
    "floor":"5",
    "capacity":"",
    "feature":""
  },
  {
    "id":110,
    "name":"961教室",
    "building":"9号館",
    "floor":"6",
    "capacity":"38",
    "feature":""
  },
  {
    "id":111,
    "name":"962教室",
    "building":"9号館",
    "floor":"6",
    "capacity":"54",
    "feature":""
  },
  {
    "id":112,
    "name":"963教室",
    "building":"9号館",
    "floor":"6",
    "capacity":"42",
    "feature":""
  },
  {
    "id":113,
    "name":"964教室",
    "building":"9号館",
    "floor":"6",
    "capacity":"42",
    "feature":""
  },
  {
    "id":114,
    "name":"965教室",
    "building":"9号館",
    "floor":"6",
    "capacity":"54",
    "feature":""
  },
  {
    "id":115,
    "name":"966教室",
    "building":"9号館",
    "floor":"6",
    "capacity":"54",
    "feature":""
  },
  {
    "id":116,
    "name":"967教室",
    "building":"9号館",
    "floor":"6",
    "capacity":"62",
    "feature":""
  },
  {
    "id":117,
    "name":"968教室",
    "building":"9号館",
    "floor":"6",
    "capacity":"44",
    "feature":""
  },
  {
    "id":118,
    "name":"971教室",
    "building":"9号館",
    "floor":"7",
    "capacity":"72",
    "feature":""
  },
  {
    "id":119,
    "name":"972教室",
    "building":"9号館",
    "floor":"7",
    "capacity":"108",
    "feature":""
  },
  {
    "id":120,
    "name":"973教室",
    "building":"9号館",
    "floor":"7",
    "capacity":"108",
    "feature":""
  },
  {
    "id":121,
    "name":"974教室",
    "building":"9号館",
    "floor":"7",
    "capacity":"72",
    "feature":""
  },
  {
    "id":122,
    "name":"975教室",
    "building":"9号館",
    "floor":"7",
    "capacity":"107",
    "feature":""
  },
  {
    "id":123,
    "name":"976教室",
    "building":"9号館",
    "floor":"7",
    "capacity":"107",
    "feature":""
  },
  {
    "id":124,
    "name":"977教室",
    "building":"9号館",
    "floor":"7",
    "capacity":"107",
    "feature":""
  },
  {
    "id":125,
    "name":"978教室",
    "building":"9号館",
    "floor":"7",
    "capacity":"99",
    "feature":""
  },
  {
    "id":126,
    "name":"979教室",
    "building":"9号館",
    "floor":"7",
    "capacity":"107",
    "feature":""
  },
  {
    "id":127,
    "name":"ゼミ98A",
    "building":"9号館",
    "floor":"8",
    "capacity":"",
    "feature":""
  },
  {
    "id":128,
    "name":"ゼミ98B",
    "building":"9号館",
    "floor":"8",
    "capacity":"",
    "feature":""
  },
  {
    "id":129,
    "name":"ゼミ98C",
    "building":"9号館",
    "floor":"8",
    "capacity":"",
    "feature":""
  },
  {
    "id":130,
    "name":"ゼミ98F",
    "building":"9号館",
    "floor":"8",
    "capacity":"",
    "feature":""
  },
  {
    "id":131,
    "name":"ゼミ101A",
    "building":"10号館",
    "floor":"1",
    "capacity":"",
    "feature":""
  },
  {
    "id":132,
    "name":"ゼミ101B",
    "building":"10号館",
    "floor":"1",
    "capacity":"",
    "feature":""
  },
  {
    "id":133,
    "name":"ゼミ101C",
    "building":"10号館",
    "floor":"1",
    "capacity":"",
    "feature":""
  },
  {
    "id":134,
    "name":"ゼミ101D",
    "building":"10号館",
    "floor":"1",
    "capacity":"",
    "feature":""
  },
  {
    "id":135,
    "name":"ゼミ101E",
    "building":"10号館",
    "floor":"1",
    "capacity":"",
    "feature":""
  },
  {
    "id":136,
    "name":"ゼミ101F",
    "building":"10号館",
    "floor":"1",
    "capacity":"",
    "feature":""
  },
  {
    "id":137,
    "name":"ゼミ101G",
    "building":"10号館",
    "floor":"1",
    "capacity":"",
    "feature":""
  },
  {
    "id":138,
    "name":"ゼミ101H",
    "building":"10号館",
    "floor":"1",
    "capacity":"",
    "feature":""
  },
  {
    "id":139,
    "name":"10101教室",
    "building":"10号館",
    "floor":"1",
    "capacity":"294",
    "feature":""
  },
  {
    "id":140,
    "name":"10102教室",
    "building":"10号館",
    "floor":"1",
    "capacity":"294",
    "feature":""
  },
  {
    "id":141,
    "name":"10103教室",
    "building":"10号館",
    "floor":"1",
    "capacity":"264",
    "feature":""
  },
  {
    "id":142,
    "name":"10201教室",
    "building":"10号館",
    "floor":"2",
    "capacity":"294",
    "feature":""
  },
  {
    "id":143,
    "name":"10202教室",
    "building":"10号館",
    "floor":"2",
    "capacity":"294",
    "feature":""
  },
  {
    "id":144,
    "name":"10203教室",
    "building":"10号館",
    "floor":"2",
    "capacity":"300",
    "feature":""
  },
  {
    "id":145,
    "name":"10204教室",
    "building":"10号館",
    "floor":"2",
    "capacity":"72",
    "feature":""
  },
  {
    "id":146,
    "name":"10205教室",
    "building":"10号館",
    "floor":"2",
    "capacity":"72",
    "feature":""
  },
  {
    "id":147,
    "name":"10206教室",
    "building":"10号館",
    "floor":"2",
    "capacity":"72",
    "feature":""
  },
  {
    "id":148,
    "name":"10207教室",
    "building":"10号館",
    "floor":"2",
    "capacity":"72",
    "feature":""
  },
  {
    "id":149,
    "name":"10208教室",
    "building":"10号館",
    "floor":"2",
    "capacity":"72",
    "feature":""
  },
  {
    "id":150,
    "name":"10209教室",
    "building":"10号館",
    "floor":"2",
    "capacity":"108",
    "feature":""
  },
  {
    "id":151,
    "name":"10210教室",
    "building":"10号館",
    "floor":"2",
    "capacity":"72",
    "feature":""
  },
  {
    "id":152,
    "name":"10211教室",
    "building":"10号館",
    "floor":"2",
    "capacity":"72",
    "feature":""
  },
  {
    "id":153,
    "name":"10212教室",
    "building":"10号館",
    "floor":"2",
    "capacity":"72",
    "feature":""
  },
  {
    "id":154,
    "name":"10213教室",
    "building":"10号館",
    "floor":"2",
    "capacity":"108",
    "feature":""
  },
  {
    "id":155,
    "name":"10214教室",
    "building":"10号館",
    "floor":"2",
    "capacity":"108",
    "feature":""
  },
  {
    "id":156,
    "name":"10215教室",
    "building":"10号館",
    "floor":"2",
    "capacity":"108",
    "feature":""
  },
  {
    "id":157,
    "name":"10301教室",
    "building":"10号館",
    "floor":"3",
    "capacity":"615",
    "feature":""
  },
  {
    "id":158,
    "name":"10302教室",
    "building":"10号館",
    "floor":"3",
    "capacity":"108",
    "feature":""
  },
  {
    "id":159,
    "name":"10303教室",
    "building":"10号館",
    "floor":"3",
    "capacity":"108",
    "feature":""
  },
  {
    "id":160,
    "name":"10304教室",
    "building":"10号館",
    "floor":"3",
    "capacity":"72",
    "feature":""
  },
  {
    "id":161,
    "name":"10305教室",
    "building":"10号館",
    "floor":"3",
    "capacity":"72",
    "feature":""
  },
  {
    "id":162,
    "name":"10306教室",
    "building":"10号館",
    "floor":"3",
    "capacity":"72",
    "feature":""
  },
  {
    "id":163,
    "name":"10307教室",
    "building":"10号館",
    "floor":"3",
    "capacity":"72",
    "feature":""
  },
  {
    "id":164,
    "name":"10308教室",
    "building":"10号館",
    "floor":"3",
    "capacity":"72",
    "feature":""
  },
  {
    "id":165,
    "name":"10309教室",
    "building":"10号館",
    "floor":"3",
    "capacity":"108",
    "feature":""
  },
  {
    "id":166,
    "name":"10310教室",
    "building":"10号館",
    "floor":"3",
    "capacity":"72",
    "feature":""
  },
  {
    "id":167,
    "name":"10311教室",
    "building":"10号館",
    "floor":"3",
    "capacity":"72",
    "feature":""
  },
  {
    "id":168,
    "name":"10312教室",
    "building":"10号館",
    "floor":"3",
    "capacity":"72",
    "feature":""
  },
  {
    "id":169,
    "name":"10313教室",
    "building":"10号館",
    "floor":"3",
    "capacity":"108",
    "feature":""
  },
  {
    "id":170,
    "name":"10314教室",
    "building":"10号館",
    "floor":"3",
    "capacity":"108",
    "feature":""
  },
  {
    "id":171,
    "name":"10315教室",
    "building":"10号館",
    "floor":"3",
    "capacity":"108",
    "feature":""
  },
  {
    "id":172,
    "name":"ゼミ105A",
    "building":"10号館",
    "floor":"5",
    "capacity":"",
    "feature":""
  },
  {
    "id":173,
    "name":"ゼミ105B",
    "building":"10号館",
    "floor":"5",
    "capacity":"",
    "feature":""
  },
  {
    "id":174,
    "name":"ゼミ105C",
    "building":"10号館",
    "floor":"5",
    "capacity":"",
    "feature":""
  },
  {
    "id":175,
    "name":"ゼミ105D",
    "building":"10号館",
    "floor":"5",
    "capacity":"",
    "feature":""
  },
  {
    "id":176,
    "name":"ゼミ105E",
    "building":"10号館",
    "floor":"5",
    "capacity":"",
    "feature":""
  },
  {
    "id":177,
    "name":"ゼミ105F",
    "building":"10号館",
    "floor":"5",
    "capacity":"",
    "feature":""
  },
  {
    "id":178,
    "name":"ゼミ105G",
    "building":"10号館",
    "floor":"5",
    "capacity":"",
    "feature":""
  },
  {
    "id":179,
    "name":"ゼミ105H",
    "building":"10号館",
    "floor":"5",
    "capacity":"",
    "feature":""
  },
  {
    "id":180,
    "name":"ゼミ105I",
    "building":"10号館",
    "floor":"5",
    "capacity":"",
    "feature":""
  },
  {
    "id":181,
    "name":"ゼミ105J",
    "building":"10号館",
    "floor":"5",
    "capacity":"",
    "feature":""
  },
  {
    "id":182,
    "name":"ゼミ105K",
    "building":"10号館",
    "floor":"5",
    "capacity":"",
    "feature":""
  },
  {
    "id":183,
    "name":"ゼミ105L",
    "building":"10号館",
    "floor":"5",
    "capacity":"",
    "feature":""
  },
  {
    "id":184,
    "name":"ゼミ105M",
    "building":"10号館",
    "floor":"5",
    "capacity":"",
    "feature":""
  },
  {
    "id":185,
    "name":"ゼミ105N",
    "building":"10号館",
    "floor":"5",
    "capacity":"",
    "feature":""
  },
  {
    "id":186,
    "name":"ゼミ105O",
    "building":"10号館",
    "floor":"5",
    "capacity":"",
    "feature":""
  },
  {
    "id":187,
    "name":"ゼミ105P",
    "building":"10号館",
    "floor":"5",
    "capacity":"",
    "feature":""
  },
  {
    "id":188,
    "name":"ゼミ105Q",
    "building":"10号館",
    "floor":"5",
    "capacity":"",
    "feature":""
  },
  {
    "id":189,
    "name":"ゼミ105R",
    "building":"10号館",
    "floor":"5",
    "capacity":"",
    "feature":""
  },
  {
    "id":190,
    "name":"ゼミ105S",
    "building":"10号館",
    "floor":"5",
    "capacity":"",
    "feature":""
  },
  {
    "id":191,
    "name":"ゼミ105T",
    "building":"10号館",
    "floor":"5",
    "capacity":"",
    "feature":""
  },
  {
    "id":192,
    "name":"ゼミ105U",
    "building":"10号館",
    "floor":"5",
    "capacity":"",
    "feature":""
  },
  {
    "id":193,
    "name":"ゼミ105V",
    "building":"10号館",
    "floor":"5",
    "capacity":"",
    "feature":""
  },
  {
    "id":194,
    "name":"ゼミ105W",
    "building":"10号館",
    "floor":"5",
    "capacity":"",
    "feature":""
  },
  {
    "id":195,
    "name":"ゼミ105X",
    "building":"10号館",
    "floor":"5",
    "capacity":"",
    "feature":""
  }
]